cr_checker/__init__.py
cr_checker/cr_checker.py
cr_checker-0.1.0.dist-info/LICENSE
cr_checker-0.1.0.dist-info/METADATA
cr_checker-0.1.0.dist-info/WHEEL
cr_checker-0.1.0.dist-info/entry_points.txt
cr_checker-0.1.0.dist-info/top_level.txt
cr_checker-0.1.0.dist-info/RECORD
