Metadata-Version: 2.1
Name: cr_checker
Version: 0.1.0
Summary: A script to check for copyright headers in files.
Home-page: https://github.com/nradakovic/copyright-checker
Author: Nikola Radakovic
Author-email: radaknikolans@gmail.com
License: MIT
Classifier: Programming Language :: Python :: 3
Classifier: License :: OSI Approved :: MIT License
Classifier: Operating System :: POSIX :: Linux
Classifier: Environment :: Console
Classifier: Intended Audience :: Developers
Requires-Python: >=3.8
License-File: LICENSE
